Workbook

Sheet Como usar
A1: Jonatas Magalhães | Consultoria em Dados, Processos e Operações
A2: Análise dos 4 Ps do marketing
B4: Para que serve
C5: Avaliar como a empresa está em Produto, Preço, Praça (onde e como vende) e Promoção (como se comunica), descobrir qual P está mais fraco e transformar isso em ações.
B7: Passo a passo
B8: 1 | C8: Leia as perguntas de cada P na aba Análise 4Ps. Pode incluir perguntas suas nas linhas livres.
B9: 2 | C9: Na coluna Como está hoje, descreva a situação real, com fatos (números, reclamações, exemplos).
B10: 3 | C10: Dê uma nota de 1 (muito ruim) a 5 (excelente) para cada pergunta.
B11: 4 | C11: Dê a importância de 1 a 3: quanto aquela pergunta pesa para o seu tipo de negócio.
B12: 5 | C12: Para as notas 1 e 2, escreva uma ação de melhoria com responsável e prazo.
B13: 6 | C13: Veja na aba Resumo o índice de cada P. O P com menor índice é a prioridade.
B14: 7 | C14: Leve as ações para o plano 5W2H e refaça a análise a cada 6 meses.
B16: Bom saber
C17: Faça a análise com pelo menos duas pessoas (por exemplo, dono e gerente) para evitar notas otimistas.
C18: Se possível, pergunte a 5 ou 10 clientes antes de dar as notas de Produto e Promoção.
C20: Células nesta cor: você digita. As demais são calculadas e não precisam ser alteradas.
C21: Procedimento de implantação: POP-F03 (baixe junto no painel). Os dados de exemplo são fictícios.
C23: jonatasmag.github.io | chazaq.adm@gmail.com | (47) 98849-9129

Sheet Análise 4Ps
A1: Jonatas Magalhães | Consultoria em Dados, Processos e Operações
A2: Análise dos 4 Ps do marketing — Empresa Exemplo (loja de bairro)
A4: P | B4: Pergunta | C4: Como está hoje | D4: Nota (1 a 5) | E4: Importância (1 a 3) | F4: Pontos | G4: Pontos possíveis | H4: Ação de melhoria | I4: Responsável | J4: Prazo
A5: Produto | B5: O mix atende ao que o cliente procura? | C5: Faltam marcas pedidas com frequência | D5: 3 | E5: 3 | F5: =IF(OR(D5="",E5=""),"",D5*E5) | G5: =IF(OR(D5="",E5=""),"",5*E5) | H5: Registrar pedidos não atendidos por 30 dias
A6: Produto | B6: A qualidade é percebida como boa? | C6: Boa avaliação, poucas trocas | D6: 4 | E6: 2 | F6: =IF(OR(D6="",E6=""),"",D6*E6) | G6: =IF(OR(D6="",E6=""),"",5*E6)
A7: Produto | B7: Embalagem, apresentação e exposição ajudam a vender? | C7: Gôndolas desorganizadas no fim do dia | D7: 2 | E7: 2 | F7: =IF(OR(D7="",E7=""),"",D7*E7) | G7: =IF(OR(D7="",E7=""),"",5*E7) | H7: Reposição e organização às 17 h
A8: Produto | B8: Existe um diferencial claro em relação aos concorrentes? | C8: Pão artesanal é o diferencial | D8: 4 | E8: 3 | F8: =IF(OR(D8="",E8=""),"",D8*E8) | G8: =IF(OR(D8="",E8=""),"",5*E8)
A9: Preço | B9: O preço cobre custos e deixa margem? | C9: Margem desconhecida em vários itens | D9: 2 | E9: 3 | F9: =IF(OR(D9="",E9=""),"",D9*E9) | G9: =IF(OR(D9="",E9=""),"",5*E9) | H9: Usar a planilha de precificação
A10: Preço | B10: O preço é competitivo com a concorrência? | C10: Alinhado nos itens básicos | D10: 4 | E10: 2 | F10: =IF(OR(D10="",E10=""),"",D10*E10) | G10: =IF(OR(D10="",E10=""),"",5*E10)
A11: Preço | B11: As formas de pagamento atendem o cliente? | C11: Aceita Pix e cartões | D11: 5 | E11: 1 | F11: =IF(OR(D11="",E11=""),"",D11*E11) | G11: =IF(OR(D11="",E11=""),"",5*E11)
A12: Preço | B12: Existe política de descontos e promoções? | C12: Descontos dados sem critério | D12: 2 | E12: 2 | F12: =IF(OR(D12="",E12=""),"",D12*E12) | G12: =IF(OR(D12="",E12=""),"",5*E12) | H12: Definir regra de desconto por margem
A13: Praça | B13: A localização e o acesso são bons? | C13: Rua movimentada, sem estacionamento | D13: 3 | E13: 2 | F13: =IF(OR(D13="",E13=""),"",D13*E13) | G13: =IF(OR(D13="",E13=""),"",5*E13)
A14: Praça | B14: O horário de funcionamento atende a demanda? | C14: Fecha às 19 h, demanda até 21 h | D14: 2 | E14: 3 | F14: =IF(OR(D14="",E14=""),"",D14*E14) | G14: =IF(OR(D14="",E14=""),"",5*E14) | H14: Testar fechamento às 21 h por 2 meses
A15: Praça | B15: Existe venda por WhatsApp, entrega ou internet? | C15: Pedidos só no balcão | D15: 1 | E15: 3 | F15: =IF(OR(D15="",E15=""),"",D15*E15) | G15: =IF(OR(D15="",E15=""),"",5*E15) | H15: Lançar pedidos por WhatsApp com entrega
A16: Praça | B16: O estoque garante o produto na prateleira? | C16: Ruptura frequente nos itens A | D16: 2 | E16: 3 | F16: =IF(OR(D16="",E16=""),"",D16*E16) | G16: =IF(OR(D16="",E16=""),"",5*E16) | H16: Contagem rotativa semanal
A17: Promoção | B17: A empresa é lembrada pelo público-alvo? | C17: Conhecida no bairro | D17: 3 | E17: 2 | F17: =IF(OR(D17="",E17=""),"",D17*E17) | G17: =IF(OR(D17="",E17=""),"",5*E17)
A18: Promoção | B18: As redes sociais são usadas com regularidade? | C18: Postagens esporádicas | D18: 1 | E18: 2 | F18: =IF(OR(D18="",E18=""),"",D18*E18) | G18: =IF(OR(D18="",E18=""),"",5*E18) | H18: Calendário de 3 posts por semana
A19: Promoção | B19: Existe programa de relacionamento ou fidelidade? | C19: Não existe | D19: 1 | E19: 2 | F19: =IF(OR(D19="",E19=""),"",D19*E19) | G19: =IF(OR(D19="",E19=""),"",5*E19) | H19: Cartão fidelidade simples
A20: Promoção | B20: A equipe de atendimento ajuda a vender? | C20: Equipe atenciosa, sem sugestão de venda | D20: 3 | E20: 2 | F20: =IF(OR(D20="",E20=""),"",D20*E20) | G20: =IF(OR(D20="",E20=""),"",5*E20) | H20: Treinar venda adicional
F21: =IF(OR(D21="",E21=""),"",D21*E21) | G21: =IF(OR(D21="",E21=""),"",5*E21)
F22: =IF(OR(D22="",E22=""),"",D22*E22) | G22: =IF(OR(D22="",E22=""),"",5*E22)
F23: =IF(OR(D23="",E23=""),"",D23*E23) | G23: =IF(OR(D23="",E23=""),"",5*E23)
F24: =IF(OR(D24="",E24=""),"",D24*E24) | G24: =IF(OR(D24="",E24=""),"",5*E24)
F25: =IF(OR(D25="",E25=""),"",D25*E25) | G25: =IF(OR(D25="",E25=""),"",5*E25)
F26: =IF(OR(D26="",E26=""),"",D26*E26) | G26: =IF(OR(D26="",E26=""),"",5*E26)
F27: =IF(OR(D27="",E27=""),"",D27*E27) | G27: =IF(OR(D27="",E27=""),"",5*E27)
F28: =IF(OR(D28="",E28=""),"",D28*E28) | G28: =IF(OR(D28="",E28=""),"",5*E28)

Sheet Resumo
A1: Jonatas Magalhães | Consultoria em Dados, Processos e Operações
A2: Análise dos 4 Ps do marketing — resultado por P
A4: P | B4: Pontos | C4: Pontos possíveis | D4: Índice (0 a 100%) | E4: Prioridade
A5: Produto | B5: =SUMIF('Análise 4Ps'!$A$5:$A$28,A5,'Análise 4Ps'!$F$5:$F$28) | C5: =SUMIF('Análise 4Ps'!$A$5:$A$28,A5,'Análise 4Ps'!$G$5:$G$28) | D5: =IFERROR(B5/C5,0) | E5: =RANK(D5,$D$5:$D$8,1)&"º"
A6: Preço | B6: =SUMIF('Análise 4Ps'!$A$5:$A$28,A6,'Análise 4Ps'!$F$5:$F$28) | C6: =SUMIF('Análise 4Ps'!$A$5:$A$28,A6,'Análise 4Ps'!$G$5:$G$28) | D6: =IFERROR(B6/C6,0) | E6: =RANK(D6,$D$5:$D$8,1)&"º"
A7: Praça | B7: =SUMIF('Análise 4Ps'!$A$5:$A$28,A7,'Análise 4Ps'!$F$5:$F$28) | C7: =SUMIF('Análise 4Ps'!$A$5:$A$28,A7,'Análise 4Ps'!$G$5:$G$28) | D7: =IFERROR(B7/C7,0) | E7: =RANK(D7,$D$5:$D$8,1)&"º"
A8: Promoção | B8: =SUMIF('Análise 4Ps'!$A$5:$A$28,A8,'Análise 4Ps'!$F$5:$F$28) | C8: =SUMIF('Análise 4Ps'!$A$5:$A$28,A8,'Análise 4Ps'!$G$5:$G$28) | D8: =IFERROR(B8/C8,0) | E8: =RANK(D8,$D$5:$D$8,1)&"º"
A9: Total | B9: =SUM(B5:B8) | C9: =SUM(C5:C8) | D9: =IFERROR(B9/C9,0)
A11: Prioridade 1º = o P com menor índice: comece as ações por ele.
