Workbook

Sheet Como usar
A1: Jonatas Magalhães | Consultoria em Dados, Processos e Operações
A2: Matriz SWOT (FOFA)
B4: Para que serve
C5: Organizar o que a empresa tem de bom e de ruim (forças e fraquezas, ambiente interno) e o que acontece fora dela (oportunidades e ameaças, ambiente externo), priorizar os fatores e definir estratégias cruzadas.
B7: Passo a passo
B8: 1 | C8: Na aba Levantamento, liste os fatores. Use frases curtas e concretas.
B9: 2 | C9: Para cada fator, escolha o tipo: Força, Fraqueza, Oportunidade ou Ameaça. O ambiente (interno ou externo) é preenchido sozinho.
B10: 3 | C10: Dê notas de impacto e de relevância de 1 a 5. A pontuação e a posição no tipo são calculadas.
B11: 4 | C11: A aba Matriz mostra os 5 fatores mais importantes de cada quadrante, prontos para apresentar.
B12: 5 | C12: Na aba Estratégias, veja a postura sugerida e escreva as ações cruzadas (FO, FA, DO e DA).
B13: 6 | C13: Leve as ações para o plano 5W2H e refaça a análise a cada 6 meses ou quando o mercado mudar.
B15: Bom saber
C16: Força e fraqueza dependem da empresa (dá para mudar). Oportunidade e ameaça vêm de fora (dá para se preparar).
C17: Evite fatores genéricos como "bom atendimento". Prefira fatos: "nota 4,8 em 120 avaliações".
C19: Células nesta cor: você digita. As demais são calculadas e não precisam ser alteradas.
C20: Procedimento de implantação: POP-F05 (baixe junto no painel). Os dados de exemplo são fictícios.
C22: jonatasmag.github.io | chazaq.adm@gmail.com | (47) 98849-9129

Sheet Levantamento
A1: Jonatas Magalhães | Consultoria em Dados, Processos e Operações
A2: Matriz SWOT (FOFA) — levantamento dos fatores
A4: Fator | B4: Tipo | C4: Ambiente | D4: Impacto (1 a 5) | E4: Relevância (1 a 5) | F4: Pontuação | G4: Posição no tipo | H4: Ordem | I4: Chave
A5: Atendimento próximo e conhecido no bairro | B5: Força | C5: =IF(B5="","",IF(OR(B5="Força",B5="Fraqueza"),"Interno","Externo")) | D5: 5 | E5: 4 | F5: =IF(OR(B5="",D5="",E5=""),"",D5*E5) | G5: =IF(F5="","",COUNTIFS($B$5:$B$44,B5,$F$5:$F$44,">"&F5)+COUNTIFS($B$5:$B$44,B5,$F$5:$F$44,F5,$H$5:$H$44,"<"&H5)+1) | H5: 1 | I5: =IF(G5="","",B5&"-"&G5)
A6: Pão artesanal com fama na região | B6: Força | C6: =IF(B6="","",IF(OR(B6="Força",B6="Fraqueza"),"Interno","Externo")) | D6: 4 | E6: 5 | F6: =IF(OR(B6="",D6="",E6=""),"",D6*E6) | G6: =IF(F6="","",COUNTIFS($B$5:$B$44,B6,$F$5:$F$44,">"&F6)+COUNTIFS($B$5:$B$44,B6,$F$5:$F$44,F6,$H$5:$H$44,"<"&H6)+1) | H6: 2 | I6: =IF(G6="","",B6&"-"&G6)
A7: Equipe estável, com pouca rotatividade | B7: Força | C7: =IF(B7="","",IF(OR(B7="Força",B7="Fraqueza"),"Interno","Externo")) | D7: 3 | E7: 3 | F7: =IF(OR(B7="",D7="",E7=""),"",D7*E7) | G7: =IF(F7="","",COUNTIFS($B$5:$B$44,B7,$F$5:$F$44,">"&F7)+COUNTIFS($B$5:$B$44,B7,$F$5:$F$44,F7,$H$5:$H$44,"<"&H7)+1) | H7: 3 | I7: =IF(G7="","",B7&"-"&G7)
A8: Ponto comercial próprio, sem aluguel | B8: Força | C8: =IF(B8="","",IF(OR(B8="Força",B8="Fraqueza"),"Interno","Externo")) | D8: 4 | E8: 3 | F8: =IF(OR(B8="",D8="",E8=""),"",D8*E8) | G8: =IF(F8="","",COUNTIFS($B$5:$B$44,B8,$F$5:$F$44,">"&F8)+COUNTIFS($B$5:$B$44,B8,$F$5:$F$44,F8,$H$5:$H$44,"<"&H8)+1) | H8: 4 | I8: =IF(G8="","",B8&"-"&G8)
A9: Sem controle de estoque: ruptura frequente | B9: Fraqueza | C9: =IF(B9="","",IF(OR(B9="Força",B9="Fraqueza"),"Interno","Externo")) | D9: 5 | E9: 5 | F9: =IF(OR(B9="",D9="",E9=""),"",D9*E9) | G9: =IF(F9="","",COUNTIFS($B$5:$B$44,B9,$F$5:$F$44,">"&F9)+COUNTIFS($B$5:$B$44,B9,$F$5:$F$44,F9,$H$5:$H$44,"<"&H9)+1) | H9: 5 | I9: =IF(G9="","",B9&"-"&G9)
A10: Margem desconhecida em vários produtos | B10: Fraqueza | C10: =IF(B10="","",IF(OR(B10="Força",B10="Fraqueza"),"Interno","Externo")) | D10: 4 | E10: 4 | F10: =IF(OR(B10="",D10="",E10=""),"",D10*E10) | G10: =IF(F10="","",COUNTIFS($B$5:$B$44,B10,$F$5:$F$44,">"&F10)+COUNTIFS($B$5:$B$44,B10,$F$5:$F$44,F10,$H$5:$H$44,"<"&H10)+1) | H10: 6 | I10: =IF(G10="","",B10&"-"&G10)
A11: Sem vendas por WhatsApp ou entrega | B11: Fraqueza | C11: =IF(B11="","",IF(OR(B11="Força",B11="Fraqueza"),"Interno","Externo")) | D11: 4 | E11: 3 | F11: =IF(OR(B11="",D11="",E11=""),"",D11*E11) | G11: =IF(F11="","",COUNTIFS($B$5:$B$44,B11,$F$5:$F$44,">"&F11)+COUNTIFS($B$5:$B$44,B11,$F$5:$F$44,F11,$H$5:$H$44,"<"&H11)+1) | H11: 7 | I11: =IF(G11="","",B11&"-"&G11)
A12: Pouca presença nas redes sociais | B12: Fraqueza | C12: =IF(B12="","",IF(OR(B12="Força",B12="Fraqueza"),"Interno","Externo")) | D12: 3 | E12: 3 | F12: =IF(OR(B12="",D12="",E12=""),"",D12*E12) | G12: =IF(F12="","",COUNTIFS($B$5:$B$44,B12,$F$5:$F$44,">"&F12)+COUNTIFS($B$5:$B$44,B12,$F$5:$F$44,F12,$H$5:$H$44,"<"&H12)+1) | H12: 8 | I12: =IF(G12="","",B12&"-"&G12)
A13: Novo condomínio com 400 famílias a 2 quadras | B13: Oportunidade | C13: =IF(B13="","",IF(OR(B13="Força",B13="Fraqueza"),"Interno","Externo")) | D13: 5 | E13: 4 | F13: =IF(OR(B13="",D13="",E13=""),"",D13*E13) | G13: =IF(F13="","",COUNTIFS($B$5:$B$44,B13,$F$5:$F$44,">"&F13)+COUNTIFS($B$5:$B$44,B13,$F$5:$F$44,F13,$H$5:$H$44,"<"&H13)+1) | H13: 9 | I13: =IF(G13="","",B13&"-"&G13)
A14: Clientes pedindo entrega pelo WhatsApp | B14: Oportunidade | C14: =IF(B14="","",IF(OR(B14="Força",B14="Fraqueza"),"Interno","Externo")) | D14: 4 | E14: 5 | F14: =IF(OR(B14="",D14="",E14=""),"",D14*E14) | G14: =IF(F14="","",COUNTIFS($B$5:$B$44,B14,$F$5:$F$44,">"&F14)+COUNTIFS($B$5:$B$44,B14,$F$5:$F$44,F14,$H$5:$H$44,"<"&H14)+1) | H14: 10 | I14: =IF(G14="","",B14&"-"&G14)
A15: Fornecedor regional oferecendo prazo maior | B15: Oportunidade | C15: =IF(B15="","",IF(OR(B15="Força",B15="Fraqueza"),"Interno","Externo")) | D15: 3 | E15: 3 | F15: =IF(OR(B15="",D15="",E15=""),"",D15*E15) | G15: =IF(F15="","",COUNTIFS($B$5:$B$44,B15,$F$5:$F$44,">"&F15)+COUNTIFS($B$5:$B$44,B15,$F$5:$F$44,F15,$H$5:$H$44,"<"&H15)+1) | H15: 11 | I15: =IF(G15="","",B15&"-"&G15)
A16: Rede de atacarejo abrindo a 3 km | B16: Ameaça | C16: =IF(B16="","",IF(OR(B16="Força",B16="Fraqueza"),"Interno","Externo")) | D16: 5 | E16: 4 | F16: =IF(OR(B16="",D16="",E16=""),"",D16*E16) | G16: =IF(F16="","",COUNTIFS($B$5:$B$44,B16,$F$5:$F$44,">"&F16)+COUNTIFS($B$5:$B$44,B16,$F$5:$F$44,F16,$H$5:$H$44,"<"&H16)+1) | H16: 12 | I16: =IF(G16="","",B16&"-"&G16)
... A18: Aplicativos de entrega levando clientes | B18: Ameaça | C18: =IF(B18="","",IF(OR(B18="Força",B18="Fraqueza"),"Interno","Externo")) | D18: 3 | E18: 3 | F18: =IF(OR(B18="",D18="",E18=""),"",D18*E18) | G18: =IF(F18="","",COUNTIFS($B$5:$B$44,B18,$F$5:$F$44,">"&F18)+COUNTIFS($B$5:$B$44,B18,$F$5:$F$44,F18,$H$5:$H$44,"<"&H18)+1) | H18: 14 | I18: =IF(G18="","",B18&"-"&G18)
C19: =IF(B19="","",IF(OR(B19="Força",B19="Fraqueza"),"Interno","Externo")) | F19: =IF(OR(B19="",D19="",E19=""),"",D19*E19) | G19: =IF(F19="","",COUNTIFS($B$5:$B$44,B19,$F$5:$F$44,">"&F19)+COUNTIFS($B$5:$B$44,B19,$F$5:$F$44,F19,$H$5:$H$44,"<"&H19)+1) | H19: 15 | I19: =IF(G19="","",B19&"-"&G19)
C20: =IF(B20="","",IF(OR(B20="Força",B20="Fraqueza"),"Interno","Externo")) | F20: =IF(OR(B20="",D20="",E20=""),"",D20*E20) | G20: =IF(F20="","",COUNTIFS($B$5:$B$44,B20,$F$5:$F$44,">"&F20)+COUNTIFS($B$5:$B$44,B20,$F$5:$F$44,F20,$H$5:$H$44,"<"&H20)+1) | H20: 16 | I20: =IF(G20="","",B20&"-"&G20)
C21: =IF(B21="","",IF(OR(B21="Força",B21="Fraqueza"),"Interno","Externo")) | F21: =IF(OR(B21="",D21="",E21=""),"",D21*E21) | G21: =IF(F21="","",COUNTIFS($B$5:$B$44,B21,$F$5:$F$44,">"&F21)+COUNTIFS($B$5:$B$44,B21,$F$5:$F$44,F21,$H$5:$H$44,"<"&H21)+1) | H21: 17 | I21: =IF(G21="","",B21&"-"&G21)
C22: =IF(B22="","",IF(OR(B22="Força",B22="Fraqueza"),"Interno","Externo")) | F22: =IF(OR(B22="",D22="",E22=""),"",D22*E22) | G22: =IF(F22="","",COUNTIFS($B$5:$B$44,B22,$F$5:$F$44,">"&F22)+COUNTIFS($B$5:$B$44,B22,$F$5:$F$44,F22,$H$5:$H$44,"<"&H22)+1) | H22: 18 | I22: =IF(G22="","",B22&"-"&G22)
C23: =IF(B23="","",IF(OR(B23="Força",B23="Fraqueza"),"Interno","Externo")) | F23: =IF(OR(B23="",D23="",E23=""),"",D23*E23) | G23: =IF(F23="","",COUNTIFS($B$5:$B$44,B23,$F$5:$F$44,">"&F23)+COUNTIFS($B$5:$B$44,B23,$F$5:$F$44,F23,$H$5:$H$44,"<"&H23)+1) | H23: 19 | I23: =IF(G23="","",B23&"-"&G23)
C24: =IF(B24="","",IF(OR(B24="Força",B24="Fraqueza"),"Interno","Externo")) | F24: =IF(OR(B24="",D24="",E24=""),"",D24*E24) | G24: =IF(F24="","",COUNTIFS($B$5:$B$44,B24,$F$5:$F$44,">"&F24)+COUNTIFS($B$5:$B$44,B24,$F$5:$F$44,F24,$H$5:$H$44,"<"&H24)+1) | H24: 20 | I24: =IF(G24="","",B24&"-"&G24)
C25: =IF(B25="","",IF(OR(B25="Força",B25="Fraqueza"),"Interno","Externo")) | F25: =IF(OR(B25="",D25="",E25=""),"",D25*E25) | G25: =IF(F25="","",COUNTIFS($B$5:$B$44,B25,$F$5:$F$44,">"&F25)+COUNTIFS($B$5:$B$44,B25,$F$5:$F$44,F25,$H$5:$H$44,"<"&H25)+1) | H25: 21 | I25: =IF(G25="","",B25&"-"&G25)
C26: =IF(B26="","",IF(OR(B26="Força",B26="Fraqueza"),"Interno","Externo")) | F26: =IF(OR(B26="",D26="",E26=""),"",D26*E26) | G26: =IF(F26="","",COUNTIFS($B$5:$B$44,B26,$F$5:$F$44,">"&F26)+COUNTIFS($B$5:$B$44,B26,$F$5:$F$44,F26,$H$5:$H$44,"<"&H26)+1) | H26: 22 | I26: =IF(G26="","",B26&"-"&G26)
C27: =IF(B27="","",IF(OR(B27="Força",B27="Fraqueza"),"Interno","Externo")) | F27: =IF(OR(B27="",D27="",E27=""),"",D27*E27) | G27: =IF(F27="","",COUNTIFS($B$5:$B$44,B27,$F$5:$F$44,">"&F27)+COUNTIFS($B$5:$B$44,B27,$F$5:$F$44,F27,$H$5:$H$44,"<"&H27)+1) | H27: 23 | I27: =IF(G27="","",B27&"-"&G27)
C28: =IF(B28="","",IF(OR(B28="Força",B28="Fraqueza"),"Interno","Externo")) | F28: =IF(OR(B28="",D28="",E28=""),"",D28*E28) | G28: =IF(F28="","",COUNTIFS($B$5:$B$44,B28,$F$5:$F$44,">"&F28)+COUNTIFS($B$5:$B$44,B28,$F$5:$F$44,F28,$H$5:$H$44,"<"&H28)+1) | H28: 24 | I28: =IF(G28="","",B28&"-"&G28)
C29: =IF(B29="","",IF(OR(B29="Força",B29="Fraqueza"),"Interno","Externo")) | F29: =IF(OR(B29="",D29="",E29=""),"",D29*E29) | G29: =IF(F29="","",COUNTIFS($B$5:$B$44,B29,$F$5:$F$44,">"&F29)+COUNTIFS($B$5:$B$44,B29,$F$5:$F$44,F29,$H$5:$H$44,"<"&H29)+1) | H29: 25 | I29: =IF(G29="","",B29&"-"&G29)
C30: =IF(B30="","",IF(OR(B30="Força",B30="Fraqueza"),"Interno","Externo")) | F30: =IF(OR(B30="",D30="",E30=""),"",D30*E30) | G30: =IF(F30="","",COUNTIFS($B$5:$B$44,B30,$F$5:$F$44,">"&F30)+COUNTIFS($B$5:$B$44,B30,$F$5:$F$44,F30,$H$5:$H$44,"<"&H30)+1) | H30: 26 | I30: =IF(G30="","",B30&"-"&G30)
... C44: =IF(B44="","",IF(OR(B44="Força",B44="Fraqueza"),"Interno","Externo")) | F44: =IF(OR(B44="",D44="",E44=""),"",D44*E44) | G44: =IF(F44="","",COUNTIFS($B$5:$B$44,B44,$F$5:$F$44,">"&F44)+COUNTIFS($B$5:$B$44,B44,$F$5:$F$44,F44,$H$5:$H$44,"<"&H44)+1) | H44: 40 | I44: =IF(G44="","",B44&"-"&G44)

Sheet Matriz
A1: Jonatas Magalhães | Consultoria em Dados, Processos e Operações
A2: Matriz SWOT (FOFA) — os 5 fatores mais importantes de cada quadrante
A4: FORÇAS (internas, ajudam) | C4: FRAQUEZAS (internas, atrapalham)
A5: 1 | B5: =IFERROR(INDEX(Levantamento!$A$5:$A$44,MATCH("Força-1",Levantamento!$I$5:$I$44,0))&" ("&INDEX(Levantamento!$F$5:$F$44,MATCH("Força-1",Levantamento!$I$5:$I$44,0))&")","") | C5: 1 | D5: =IFERROR(INDEX(Levantamento!$A$5:$A$44,MATCH("Fraqueza-1",Levantamento!$I$5:$I$44,0))&" ("&INDEX(Levantamento!$F$5:$F$44,MATCH("Fraqueza-1",Levantamento!$I$5:$I$44,0))&")","")
A6: 2 | B6: =IFERROR(INDEX(Levantamento!$A$5:$A$44,MATCH("Força-2",Levantamento!$I$5:$I$44,0))&" ("&INDEX(Levantamento!$F$5:$F$44,MATCH("Força-2",Levantamento!$I$5:$I$44,0))&")","") | C6: 2 | D6: =IFERROR(INDEX(Levantamento!$A$5:$A$44,MATCH("Fraqueza-2",Levantamento!$I$5:$I$44,0))&" ("&INDEX(Levantamento!$F$5:$F$44,MATCH("Fraqueza-2",Levantamento!$I$5:$I$44,0))&")","")
A7: 3 | B7: =IFERROR(INDEX(Levantamento!$A$5:$A$44,MATCH("Força-3",Levantamento!$I$5:$I$44,0))&" ("&INDEX(Levantamento!$F$5:$F$44,MATCH("Força-3",Levantamento!$I$5:$I$44,0))&")","") | C7: 3 | D7: =IFERROR(INDEX(Levantamento!$A$5:$A$44,MATCH("Fraqueza-3",Levantamento!$I$5:$I$44,0))&" ("&INDEX(Levantamento!$F$5:$F$44,MATCH("Fraqueza-3",Levantamento!$I$5:$I$44,0))&")","")
A8: 4 | B8: =IFERROR(INDEX(Levantamento!$A$5:$A$44,MATCH("Força-4",Levantamento!$I$5:$I$44,0))&" ("&INDEX(Levantamento!$F$5:$F$44,MATCH("Força-4",Levantamento!$I$5:$I$44,0))&")","") | C8: 4 | D8: =IFERROR(INDEX(Levantamento!$A$5:$A$44,MATCH("Fraqueza-4",Levantamento!$I$5:$I$44,0))&" ("&INDEX(Levantamento!$F$5:$F$44,MATCH("Fraqueza-4",Levantamento!$I$5:$I$44,0))&")","")
A9: 5 | B9: =IFERROR(INDEX(Levantamento!$A$5:$A$44,MATCH("Força-5",Levantamento!$I$5:$I$44,0))&" ("&INDEX(Levantamento!$F$5:$F$44,MATCH("Força-5",Levantamento!$I$5:$I$44,0))&")","") | C9: 5 | D9: =IFERROR(INDEX(Levantamento!$A$5:$A$44,MATCH("Fraqueza-5",Levantamento!$I$5:$I$44,0))&" ("&INDEX(Levantamento!$F$5:$F$44,MATCH("Fraqueza-5",Levantamento!$I$5:$I$44,0))&")","")
A12: OPORTUNIDADES (externas, ajudam) | C12: AMEAÇAS (externas, atrapalham)
A13: 1 | B13: =IFERROR(INDEX(Levantamento!$A$5:$A$44,MATCH("Oportunidade-1",Levantamento!$I$5:$I$44,0))&" ("&INDEX(Levantamento!$F$5:$F$44,MATCH("Oportunidade-1",Levantamento!$I$5:$I$44,0))&")","") | C13: 1 | D13: =IFERROR(INDEX(Levantamento!$A$5:$A$44,MATCH("Ameaça-1",Levantamento!$I$5:$I$44,0))&" ("&INDEX(Levantamento!$F$5:$F$44,MATCH("Ameaça-1",Levantamento!$I$5:$I$44,0))&")","")
A14: 2 | B14: =IFERROR(INDEX(Levantamento!$A$5:$A$44,MATCH("Oportunidade-2",Levantamento!$I$5:$I$44,0))&" ("&INDEX(Levantamento!$F$5:$F$44,MATCH("Oportunidade-2",Levantamento!$I$5:$I$44,0))&")","") | C14: 2 | D14: =IFERROR(INDEX(Levantamento!$A$5:$A$44,MATCH("Ameaça-2",Levantamento!$I$5:$I$44,0))&" ("&INDEX(Levantamento!$F$5:$F$44,MATCH("Ameaça-2",Levantamento!$I$5:$I$44,0))&")","")
A15: 3 | B15: =IFERROR(INDEX(Levantamento!$A$5:$A$44,MATCH("Oportunidade-3",Levantamento!$I$5:$I$44,0))&" ("&INDEX(Levantamento!$F$5:$F$44,MATCH("Oportunidade-3",Levantamento!$I$5:$I$44,0))&")","") | C15: 3 | D15: =IFERROR(INDEX(Levantamento!$A$5:$A$44,MATCH("Ameaça-3",Levantamento!$I$5:$I$44,0))&" ("&INDEX(Levantamento!$F$5:$F$44,MATCH("Ameaça-3",Levantamento!$I$5:$I$44,0))&")","")
A16: 4 | B16: =IFERROR(INDEX(Levantamento!$A$5:$A$44,MATCH("Oportunidade-4",Levantamento!$I$5:$I$44,0))&" ("&INDEX(Levantamento!$F$5:$F$44,MATCH("Oportunidade-4",Levantamento!$I$5:$I$44,0))&")","") | C16: 4 | D16: =IFERROR(INDEX(Levantamento!$A$5:$A$44,MATCH("Ameaça-4",Levantamento!$I$5:$I$44,0))&" ("&INDEX(Levantamento!$F$5:$F$44,MATCH("Ameaça-4",Levantamento!$I$5:$I$44,0))&")","")
A17: 5 | B17: =IFERROR(INDEX(Levantamento!$A$5:$A$44,MATCH("Oportunidade-5",Levantamento!$I$5:$I$44,0))&" ("&INDEX(Levantamento!$F$5:$F$44,MATCH("Oportunidade-5",Levantamento!$I$5:$I$44,0))&")","") | C17: 5 | D17: =IFERROR(INDEX(Levantamento!$A$5:$A$44,MATCH("Ameaça-5",Levantamento!$I$5:$I$44,0))&" ("&INDEX(Levantamento!$F$5:$F$44,MATCH("Ameaça-5",Levantamento!$I$5:$I$44,0))&")","")
B19: Entre parênteses: pontuação (impacto × relevância).

Sheet Estratégias
A1: Jonatas Magalhães | Consultoria em Dados, Processos e Operações
A2: Matriz SWOT (FOFA) — estratégias cruzadas e postura sugerida
A4: Quadrante | B4: Pontuação total | C4: Leitura
A5: Forças | B5: =SUMIF(Levantamento!$B$5:$B$44,"Força",Levantamento!$F$5:$F$44) | C5: Soma das pontuações das forças
A6: Fraquezas | B6: =SUMIF(Levantamento!$B$5:$B$44,"Fraqueza",Levantamento!$F$5:$F$44) | C6: Soma das pontuações das fraquezas
A7: Oportunidades | B7: =SUMIF(Levantamento!$B$5:$B$44,"Oportunidade",Levantamento!$F$5:$F$44) | C7: Soma das pontuações das oportunidades
A8: Ameaças | B8: =SUMIF(Levantamento!$B$5:$B$44,"Ameaça",Levantamento!$F$5:$F$44) | C8: Soma das pontuações das ameaças
A10: Postura estratégica sugerida | B10: =IF(B5>=B6,IF(B7>=B8,"Desenvolvimento","Manutenção"),IF(B7>=B8,"Crescimento","Sobrevivência"))
A11: Desenvolvimento: forças > fraquezas e oportunidades > ameaças — use as forças para crescer.
A12: Manutenção: forças > fraquezas, mas ameaças > oportunidades — proteja a posição.
A13: Crescimento: fraquezas > forças, com oportunidades > ameaças — corrija as fraquezas para aproveitar o mercado.
A14: Sobrevivência: fraquezas > forças e ameaças > oportunidades — reduza riscos e custos primeiro.
A16: Estratégia cruzada | B16: Ação | C16: Responsável e prazo
A17: FO: usar forças para aproveitar oportunidades | B17: Lançar pedidos de pão artesanal por WhatsApp para o novo condomínio | C17: Carla, até 15/12
A18: FA: usar forças para reduzir ameaças | B18: Reforçar o atendimento próximo como diferencial frente ao atacarejo | C18: Carla, contínuo
A19: DO: corrigir fraquezas aproveitando oportunidades | B19: Implantar controle de estoque antes de começar as entregas | C19: Ana, até 30/11
A20: DA: reduzir fraquezas para se proteger das ameaças | B20: Revisar preços com a planilha de precificação por causa da alta de custos | C20: Bruno, até 30/11
