Workbook

Sheet Como usar
A1: Jonatas Magalhães | Consultoria em Dados, Processos e Operações
A2: Precificação de produtos
B4: Para que serve
C5: Calcular o preço de venda que paga o custo do produto, a parte dele nas despesas fixas, os impostos e as taxas, e ainda deixa o lucro desejado. Mostra também a margem real dos preços que você já pratica e compara com o concorrente.
B7: Passo a passo
B8: 1 | C8: Na aba Parâmetros, digite o faturamento médio mensal e cada custo fixo do mês.
B9: 2 | C9: Ainda em Parâmetros, digite os percentuais de impostos, taxa de cartão, comissão e outras despesas variáveis.
B10: 3 | C10: Defina a margem de lucro desejada. A soma dos percentuais precisa ficar abaixo de 100%.
B11: 4 | C11: Na aba Precificação, troque os produtos de exemplo pelos seus: nome, custo de compra e frete ou outros custos por unidade.
B12: 5 | C12: Leia o preço sugerido. Ele já cobre custo, despesas fixas, despesas variáveis e lucro.
B13: 6 | C13: Digite o preço que você pratica hoje. A coluna Situação mostra se a margem está OK, abaixo da meta ou dando prejuízo.
B14: 7 | C14: Se quiser, digite o preço do concorrente para ver a diferença em %.
B15: 8 | C15: Revise os parâmetros todo mês e os custos de compra sempre que o fornecedor reajustar.
B17: Bom saber
C18: Markup divisor: preço = custo ÷ (1 − custos fixos % − despesas variáveis % − margem %).
C19: Para um produto específico, você pode digitar outra margem na coluna Margem desejada (por exemplo, menor para itens de giro e maior para itens exclusivos).
C20: Preço abaixo do sugerido não é proibido, mas precisa ser uma decisão consciente, com volume que compense.
C22: Células nesta cor: você digita. As demais são calculadas e não precisam ser alteradas.
C23: Procedimento de implantação: POP-F01 (baixe junto no painel). Os dados de exemplo são fictícios.
C25: jonatasmag.github.io | chazaq.adm@gmail.com | (47) 98849-9129

Sheet Parâmetros
A1: Jonatas Magalhães | Consultoria em Dados, Processos e Operações
A2: Precificação de produtos — parâmetros da empresa
A4: Faturamento
A5: Faturamento médio mensal | B5: 180000 | C5: Média dos últimos 3 a 6 meses.
A7: Custos fixos mensais
A8: Aluguel e condomínio | B8: 4500
A9: Salários e encargos | B9: 12000
A10: Pró-labore | B10: 5000
A11: Energia, água e internet | B11: 1300
A12: Contador e sistemas | B12: 1100
A13: Outros custos fixos | B13: 900
A14: Total de custos fixos | B14: =SUM(B8:B13) | C14: Soma das linhas acima.
A15: Custos fixos em % do faturamento | B15: =IFERROR(B14/B5,0) | C15: Quanto de cada venda vai para pagar a estrutura.
A17: Despesas variáveis (em % do preço de venda)
A18: Impostos sobre a venda (ex.: Simples Nacional) | B18: 0.06 | C18: Use a alíquota efetiva da sua faixa.
A19: Taxa de cartão e meios de pagamento | B19: 0.025 | C19: Média ponderada das formas de pagamento.
A20: Comissão de vendas | B20: 0 | C20: Deixe 0% se não houver comissão.
A21: Embalagem, frete e outras | B21: 0.01
A22: Total de despesas variáveis | B22: =SUM(B18:B21)
A24: Lucro
A25: Margem de lucro desejada | B25: 0.08 | C25: Lucro líquido que você quer em cada venda.
A27: Soma dos percentuais | B27: =B15+B22+B25 | C27: Precisa ficar abaixo de 100%.
A28: Markup divisor | B28: =1-B27 | C28: Preço = custo ÷ markup divisor.
A29: Markup multiplicador | B29: =IFERROR(1/B28,"Revise") | C29: Preço = custo × markup multiplicador.

Sheet Precificação
A1: Jonatas Magalhães | Consultoria em Dados, Processos e Operações
A2: Precificação de produtos — preço sugerido e margem real
A4: Produto | B4: Custo de compra (R$) | C4: Frete e outros custos por unidade (R$) | D4: Custo total unitário (R$) | E4: Margem desejada | F4: Markup divisor | G4: Preço sugerido (R$) | H4: Preço praticado (R$) | I4: Margem real | J4: Situação | K4: Preço do concorrente (R$) | L4: Diferença para o concorrente
A5: Café torrado 500 g | B5: 11.9 | C5: 0.6 | D5: =B5+C5 | E5: =Parâmetros!$B$25 | F5: =1-(Parâmetros!$B$15+Parâmetros!$B$22+E5) | G5: =IF(F5<=0,"Revise %",ROUND(D5/F5,2)) | H5: 19.9 | I5: =IF(H5>0,(H5*(1-Parâmetros!$B$15-Parâmetros!$B$22)-D5)/H5,"") | J5: =IF(H5="","",IF(I5<0,"Prejuízo",IF(I5<E5,"Abaixo da meta","OK"))) | K5: 21.5 | L5: =IF(OR(H5="",K5=""),"",H5/K5-1)
A6: Açúcar cristal 5 kg | B6: 14.2 | C6: 0.8 | D6: =B6+C6 | E6: =Parâmetros!$B$25 | F6: =1-(Parâmetros!$B$15+Parâmetros!$B$22+E6) | G6: =IF(F6<=0,"Revise %",ROUND(D6/F6,2)) | H6: 22.9 | I6: =IF(H6>0,(H6*(1-Parâmetros!$B$15-Parâmetros!$B$22)-D6)/H6,"") | J6: =IF(H6="","",IF(I6<0,"Prejuízo",IF(I6<E6,"Abaixo da meta","OK"))) | K6: 21.99 | L6: =IF(OR(H6="",K6=""),"",H6/K6-1)
A7: Arroz tipo 1 5 kg | B7: 21.5 | C7: 1 | D7: =B7+C7 | E7: =Parâmetros!$B$25 | F7: =1-(Parâmetros!$B$15+Parâmetros!$B$22+E7) | G7: =IF(F7<=0,"Revise %",ROUND(D7/F7,2)) | H7: 31.9 | I7: =IF(H7>0,(H7*(1-Parâmetros!$B$15-Parâmetros!$B$22)-D7)/H7,"") | J7: =IF(H7="","",IF(I7<0,"Prejuízo",IF(I7<E7,"Abaixo da meta","OK"))) | K7: 29.9 | L7: =IF(OR(H7="",K7=""),"",H7/K7-1)
A8: Feijão carioca 1 kg | B8: 6.1 | C8: 0.3 | D8: =B8+C8 | E8: =Parâmetros!$B$25 | F8: =1-(Parâmetros!$B$15+Parâmetros!$B$22+E8) | G8: =IF(F8<=0,"Revise %",ROUND(D8/F8,2)) | H8: 9.49 | I8: =IF(H8>0,(H8*(1-Parâmetros!$B$15-Parâmetros!$B$22)-D8)/H8,"") | J8: =IF(H8="","",IF(I8<0,"Prejuízo",IF(I8<E8,"Abaixo da meta","OK"))) | K8: 8.99 | L8: =IF(OR(H8="",K8=""),"",H8/K8-1)
A9: Óleo de soja 900 ml | B9: 5.4 | C9: 0.3 | D9: =B9+C9 | E9: =Parâmetros!$B$25 | F9: =1-(Parâmetros!$B$15+Parâmetros!$B$22+E9) | G9: =IF(F9<=0,"Revise %",ROUND(D9/F9,2)) | H9: 8.49 | I9: =IF(H9>0,(H9*(1-Parâmetros!$B$15-Parâmetros!$B$22)-D9)/H9,"") | J9: =IF(H9="","",IF(I9<0,"Prejuízo",IF(I9<E9,"Abaixo da meta","OK"))) | K9: 7.99 | L9: =IF(OR(H9="",K9=""),"",H9/K9-1)
A10: Detergente 500 ml | B10: 1.75 | C10: 0.1 | D10: =B10+C10 | E10: =Parâmetros!$B$25 | F10: =1-(Parâmetros!$B$15+Parâmetros!$B$22+E10) | G10: =IF(F10<=0,"Revise %",ROUND(D10/F10,2)) | H10: 3.29 | I10: =IF(H10>0,(H10*(1-Parâmetros!$B$15-Parâmetros!$B$22)-D10)/H10,"") | J10: =IF(H10="","",IF(I10<0,"Prejuízo",IF(I10<E10,"Abaixo da meta","OK"))) | K10: 2.99 | L10: =IF(OR(H10="",K10=""),"",H10/K10-1)
A11: Sabão em pó 1,6 kg | B11: 13.8 | C11: 0.6 | D11: =B11+C11 | E11: =Parâmetros!$B$25 | F11: =1-(Parâmetros!$B$15+Parâmetros!$B$22+E11) | G11: =IF(F11<=0,"Revise %",ROUND(D11/F11,2)) | H11: 21.9 | I11: =IF(H11>0,(H11*(1-Parâmetros!$B$15-Parâmetros!$B$22)-D11)/H11,"") | J11: =IF(H11="","",IF(I11<0,"Prejuízo",IF(I11<E11,"Abaixo da meta","OK"))) | K11: 22.9 | L11: =IF(OR(H11="",K11=""),"",H11/K11-1)
A12: Papel higiênico 12 rolos | B12: 15.9 | C12: 0.9 | D12: =B12+C12 | E12: =Parâmetros!$B$25 | F12: =1-(Parâmetros!$B$15+Parâmetros!$B$22+E12) | G12: =IF(F12<=0,"Revise %",ROUND(D12/F12,2)) | H12: 23.9 | I12: =IF(H12>0,(H12*(1-Parâmetros!$B$15-Parâmetros!$B$22)-D12)/H12,"") | J12: =IF(H12="","",IF(I12<0,"Prejuízo",IF(I12<E12,"Abaixo da meta","OK"))) | K12: 24.9 | L12: =IF(OR(H12="",K12=""),"",H12/K12-1)
A13: Biscoito recheado 140 g | B13: 2.1 | C13: 0.1 | D13: =B13+C13 | E13: =Parâmetros!$B$25 | F13: =1-(Parâmetros!$B$15+Parâmetros!$B$22+E13) | G13: =IF(F13<=0,"Revise %",ROUND(D13/F13,2)) | H13: 3.79 | I13: =IF(H13>0,(H13*(1-Parâmetros!$B$15-Parâmetros!$B$22)-D13)/H13,"") | J13: =IF(H13="","",IF(I13<0,"Prejuízo",IF(I13<E13,"Abaixo da meta","OK"))) | K13: 3.49 | L13: =IF(OR(H13="",K13=""),"",H13/K13-1)
A14: Refrigerante 2 L | B14: 6.4 | C14: 0.4 | D14: =B14+C14 | E14: =Parâmetros!$B$25 | F14: =1-(Parâmetros!$B$15+Parâmetros!$B$22+E14) | G14: =IF(F14<=0,"Revise %",ROUND(D14/F14,2)) | H14: 7.99 | I14: =IF(H14>0,(H14*(1-Parâmetros!$B$15-Parâmetros!$B$22)-D14)/H14,"") | J14: =IF(H14="","",IF(I14<0,"Prejuízo",IF(I14<E14,"Abaixo da meta","OK"))) | K14: 7.49 | L14: =IF(OR(H14="",K14=""),"",H14/K14-1)
D15: =IF(B15="","",B15+C15) | E15: =IF(B15="","",Parâmetros!$B$25) | F15: =IF(B15="","",1-(Parâmetros!$B$15+Parâmetros!$B$22+E15)) | G15: =IF(B15="","",IF(F15<=0,"Revise %",ROUND(D15/F15,2))) | I15: =IF(OR(B15="",H15=""),"",(H15*(1-Parâmetros!$B$15-Parâmetros!$B$22)-D15)/H15) | J15: =IF(OR(B15="",H15=""),"",IF(I15<0,"Prejuízo",IF(I15<E15,"Abaixo da meta","OK"))) | L15: =IF(OR(H15="",K15=""),"",H15/K15-1)
D16: =IF(B16="","",B16+C16) | E16: =IF(B16="","",Parâmetros!$B$25) | F16: =IF(B16="","",1-(Parâmetros!$B$15+Parâmetros!$B$22+E16)) | G16: =IF(B16="","",IF(F16<=0,"Revise %",ROUND(D16/F16,2))) | I16: =IF(OR(B16="",H16=""),"",(H16*(1-Parâmetros!$B$15-Parâmetros!$B$22)-D16)/H16) | J16: =IF(OR(B16="",H16=""),"",IF(I16<0,"Prejuízo",IF(I16<E16,"Abaixo da meta","OK"))) | L16: =IF(OR(H16="",K16=""),"",H16/K16-1)
D17: =IF(B17="","",B17+C17) | E17: =IF(B17="","",Parâmetros!$B$25) | F17: =IF(B17="","",1-(Parâmetros!$B$15+Parâmetros!$B$22+E17)) | G17: =IF(B17="","",IF(F17<=0,"Revise %",ROUND(D17/F17,2))) | I17: =IF(OR(B17="",H17=""),"",(H17*(1-Parâmetros!$B$15-Parâmetros!$B$22)-D17)/H17) | J17: =IF(OR(B17="",H17=""),"",IF(I17<0,"Prejuízo",IF(I17<E17,"Abaixo da meta","OK"))) | L17: =IF(OR(H17="",K17=""),"",H17/K17-1)
D18: =IF(B18="","",B18+C18) | E18: =IF(B18="","",Parâmetros!$B$25) | F18: =IF(B18="","",1-(Parâmetros!$B$15+Parâmetros!$B$22+E18)) | G18: =IF(B18="","",IF(F18<=0,"Revise %",ROUND(D18/F18,2))) | I18: =IF(OR(B18="",H18=""),"",(H18*(1-Parâmetros!$B$15-Parâmetros!$B$22)-D18)/H18) | J18: =IF(OR(B18="",H18=""),"",IF(I18<0,"Prejuízo",IF(I18<E18,"Abaixo da meta","OK"))) | L18: =IF(OR(H18="",K18=""),"",H18/K18-1)
D19: =IF(B19="","",B19+C19) | E19: =IF(B19="","",Parâmetros!$B$25) | F19: =IF(B19="","",1-(Parâmetros!$B$15+Parâmetros!$B$22+E19)) | G19: =IF(B19="","",IF(F19<=0,"Revise %",ROUND(D19/F19,2))) | I19: =IF(OR(B19="",H19=""),"",(H19*(1-Parâmetros!$B$15-Parâmetros!$B$22)-D19)/H19) | J19: =IF(OR(B19="",H19=""),"",IF(I19<0,"Prejuízo",IF(I19<E19,"Abaixo da meta","OK"))) | L19: =IF(OR(H19="",K19=""),"",H19/K19-1)
D20: =IF(B20="","",B20+C20) | E20: =IF(B20="","",Parâmetros!$B$25) | F20: =IF(B20="","",1-(Parâmetros!$B$15+Parâmetros!$B$22+E20)) | G20: =IF(B20="","",IF(F20<=0,"Revise %",ROUND(D20/F20,2))) | I20: =IF(OR(B20="",H20=""),"",(H20*(1-Parâmetros!$B$15-Parâmetros!$B$22)-D20)/H20) | J20: =IF(OR(B20="",H20=""),"",IF(I20<0,"Prejuízo",IF(I20<E20,"Abaixo da meta","OK"))) | L20: =IF(OR(H20="",K20=""),"",H20/K20-1)
D21: =IF(B21="","",B21+C21) | E21: =IF(B21="","",Parâmetros!$B$25) | F21: =IF(B21="","",1-(Parâmetros!$B$15+Parâmetros!$B$22+E21)) | G21: =IF(B21="","",IF(F21<=0,"Revise %",ROUND(D21/F21,2))) | I21: =IF(OR(B21="",H21=""),"",(H21*(1-Parâmetros!$B$15-Parâmetros!$B$22)-D21)/H21) | J21: =IF(OR(B21="",H21=""),"",IF(I21<0,"Prejuízo",IF(I21<E21,"Abaixo da meta","OK"))) | L21: =IF(OR(H21="",K21=""),"",H21/K21-1)
D22: =IF(B22="","",B22+C22) | E22: =IF(B22="","",Parâmetros!$B$25) | F22: =IF(B22="","",1-(Parâmetros!$B$15+Parâmetros!$B$22+E22)) | G22: =IF(B22="","",IF(F22<=0,"Revise %",ROUND(D22/F22,2))) | I22: =IF(OR(B22="",H22=""),"",(H22*(1-Parâmetros!$B$15-Parâmetros!$B$22)-D22)/H22) | J22: =IF(OR(B22="",H22=""),"",IF(I22<0,"Prejuízo",IF(I22<E22,"Abaixo da meta","OK"))) | L22: =IF(OR(H22="",K22=""),"",H22/K22-1)
D23: =IF(B23="","",B23+C23) | E23: =IF(B23="","",Parâmetros!$B$25) | F23: =IF(B23="","",1-(Parâmetros!$B$15+Parâmetros!$B$22+E23)) | G23: =IF(B23="","",IF(F23<=0,"Revise %",ROUND(D23/F23,2))) | I23: =IF(OR(B23="",H23=""),"",(H23*(1-Parâmetros!$B$15-Parâmetros!$B$22)-D23)/H23) | J23: =IF(OR(B23="",H23=""),"",IF(I23<0,"Prejuízo",IF(I23<E23,"Abaixo da meta","OK"))) | L23: =IF(OR(H23="",K23=""),"",H23/K23-1)
D24: =IF(B24="","",B24+C24) | E24: =IF(B24="","",Parâmetros!$B$25) | F24: =IF(B24="","",1-(Parâmetros!$B$15+Parâmetros!$B$22+E24)) | G24: =IF(B24="","",IF(F24<=0,"Revise %",ROUND(D24/F24,2))) | I24: =IF(OR(B24="",H24=""),"",(H24*(1-Parâmetros!$B$15-Parâmetros!$B$22)-D24)/H24) | J24: =IF(OR(B24="",H24=""),"",IF(I24<0,"Prejuízo",IF(I24<E24,"Abaixo da meta","OK"))) | L24: =IF(OR(H24="",K24=""),"",H24/K24-1)
D25: =IF(B25="","",B25+C25) | E25: =IF(B25="","",Parâmetros!$B$25) | F25: =IF(B25="","",1-(Parâmetros!$B$15+Parâmetros!$B$22+E25)) | G25: =IF(B25="","",IF(F25<=0,"Revise %",ROUND(D25/F25,2))) | I25: =IF(OR(B25="",H25=""),"",(H25*(1-Parâmetros!$B$15-Parâmetros!$B$22)-D25)/H25) | J25: =IF(OR(B25="",H25=""),"",IF(I25<0,"Prejuízo",IF(I25<E25,"Abaixo da meta","OK"))) | L25: =IF(OR(H25="",K25=""),"",H25/K25-1)
D26: =IF(B26="","",B26+C26) | E26: =IF(B26="","",Parâmetros!$B$25) | F26: =IF(B26="","",1-(Parâmetros!$B$15+Parâmetros!$B$22+E26)) | G26: =IF(B26="","",IF(F26<=0,"Revise %",ROUND(D26/F26,2))) | I26: =IF(OR(B26="",H26=""),"",(H26*(1-Parâmetros!$B$15-Parâmetros!$B$22)-D26)/H26) | J26: =IF(OR(B26="",H26=""),"",IF(I26<0,"Prejuízo",IF(I26<E26,"Abaixo da meta","OK"))) | L26: =IF(OR(H26="",K26=""),"",H26/K26-1)
... D44: =IF(B44="","",B44+C44) | E44: =IF(B44="","",Parâmetros!$B$25) | F44: =IF(B44="","",1-(Parâmetros!$B$15+Parâmetros!$B$22+E44)) | G44: =IF(B44="","",IF(F44<=0,"Revise %",ROUND(D44/F44,2))) | I44: =IF(OR(B44="",H44=""),"",(H44*(1-Parâmetros!$B$15-Parâmetros!$B$22)-D44)/H44) | J44: =IF(OR(B44="",H44=""),"",IF(I44<0,"Prejuízo",IF(I44<E44,"Abaixo da meta","OK"))) | L44: =IF(OR(H44="",K44=""),"",H44/K44-1)
A46: Resumo
A47: Produtos cadastrados | B47: =COUNTA(A5:A44)
A48: Com margem OK | B48: =COUNTIF(J5:J44,"OK")
A49: Abaixo da meta | B49: =COUNTIF(J5:J44,"Abaixo da meta")
A50: Com prejuízo | B50: =COUNTIF(J5:J44,"Prejuízo")
A51: Margem real média | B51: =IFERROR(AVERAGE(I5:I44),0)
